torchium/__init__.py
torchium/py.typed
torchium/pytest.ini
torchium/benchmarks/__init__.py
torchium/benchmarks/optimizer_benchmark.py
torchium/benchmarks/quick_benchmark.py
torchium/docs/source/conf.py
torchium/docs/source/conf_pytheme.py
torchium/docs/source/index.rst
torchium/docs/source/_static/custom.css
torchium/docs/source/_static/logo.png
torchium/docs/source/api/losses.rst
torchium/docs/source/api/optimizers.rst
torchium/docs/source/examples/benchmarks.rst
torchium/docs/source/examples/computer_vision.rst
torchium/docs/source/examples/generative_models.rst
torchium/docs/source/examples/nlp.rst
torchium/docs/source/examples/optimization_comparison.rst
torchium/docs/source/tutorials/advanced_usage.rst
torchium/docs/source/tutorials/cuda_integration.rst
torchium/docs/source/tutorials/cython_optimizations.rst
torchium/docs/source/tutorials/domain_specific_usage.rst
torchium/docs/source/tutorials/performance_guide.rst
torchium/docs/source/tutorials/quickstart.rst
torchium/losses/__init__.py
torchium/losses/classification/__init__.py
torchium/losses/classification/cross_entropy.py
torchium/losses/classification/margin_based.py
torchium/losses/classification/ranking.py
torchium/losses/computer_vision/__init__.py
torchium/losses/computer_vision/detection.py
torchium/losses/computer_vision/segmentation.py
torchium/losses/computer_vision/style_transfer.py
torchium/losses/computer_vision/super_resolution.py
torchium/losses/domain_specific/__init__.py
torchium/losses/generative/__init__.py
torchium/losses/metric_learning/__init__.py
torchium/losses/multi_task/__init__.py
torchium/losses/nlp/__init__.py
torchium/losses/regression/__init__.py
torchium/losses/regression/mse_variants.py
torchium/losses/regression/robust.py
torchium/optimizers/__init__.py
torchium/optimizers/adaptive/__init__.py
torchium/optimizers/adaptive/adagrad_variants.py
torchium/optimizers/adaptive/adam_variants.py
torchium/optimizers/adaptive/rmsprop_variants.py
torchium-0.1.5.dist-info/METADATA
torchium-0.1.5.dist-info/WHEEL
torchium-0.1.5.dist-info/top_level.txt
torchium-0.1.5.dist-info/RECORD
