Metadata-Version: 2.4
Name: torchium
Version: 0.1.5
Summary: Comprehensive PyTorch Extension Library with 200+ Optimizers and 200+ Loss Functions
Author-email: Vishesh Yadav <sciencely98@gmail.com>
Maintainer-email: Vishesh Yadav <sciencely98@gmail.com>
License: MIT
Project-URL: Homepage, https://github.com/vishesh9131/torchium
Project-URL: Documentation, https://torchium.readthedocs.io
Project-URL: Repository, https://github.com/vishesh9131/torchium
Project-URL: Bug Tracker, https://github.com/vishesh9131/torchium/issues
Project-URL: Source Code, https://github.com/vishesh9131/torchium
Keywords: pytorch,deep-learning,machine-learning,optimization,loss-functions,optimizers,neural-networks,ai,ml
Classifier: Development Status :: 3 - Alpha
Classifier: Intended Audience :: Developers
Classifier: Intended Audience :: Science/Research
Classifier: Operating System :: OS Independent
Classifier: Programming Language :: Python :: 3
Classifier: Programming Language :: Python :: 3.8
Classifier: Programming Language :: Python :: 3.9
Classifier: Programming Language :: Python :: 3.10
Classifier: Programming Language :: Python :: 3.11
Classifier: Topic :: Scientific/Engineering :: Artificial Intelligence
Classifier: Topic :: Software Development :: Libraries :: Python Modules
Requires-Python: >=3.8
Requires-Dist: torch>=1.9.0
Requires-Dist: numpy>=1.21.0
Provides-Extra: dev
Requires-Dist: pytest>=6.0; extra == "dev"
Requires-Dist: pytest-cov>=2.0; extra == "dev"
Requires-Dist: black>=21.0; extra == "dev"
Requires-Dist: flake8>=3.8; extra == "dev"
Requires-Dist: isort>=5.0; extra == "dev"
Requires-Dist: mypy>=0.812; extra == "dev"
Requires-Dist: pre-commit>=2.0; extra == "dev"
Provides-Extra: docs
Requires-Dist: sphinx>=4.0; extra == "docs"
Requires-Dist: sphinx-rtd-theme>=1.0; extra == "docs"
Requires-Dist: sphinx-autodoc-typehints>=1.0; extra == "docs"
Requires-Dist: myst-parser>=0.15; extra == "docs"
Provides-Extra: full
Requires-Dist: scipy>=1.7.0; extra == "full"
Requires-Dist: scikit-learn>=1.0.0; extra == "full"
Requires-Dist: matplotlib>=3.3.0; extra == "full"
Requires-Dist: seaborn>=0.11.0; extra == "full"
Requires-Dist: pandas>=1.3.0; extra == "full"
Requires-Dist: tqdm>=4.60.0; extra == "full"
